facetoolsz/__init__.py
facetoolsz/ZIMG/ZIMG.py
facetoolsz/ZIMG/ZJPG.py
facetoolsz/ZIMG/__init__.py
facetoolsz/core/__init__.py
facetoolsz/core/cv2ex.py
facetoolsz/core/osex.py
facetoolsz/core/pathex.py
facetoolsz/core/randomex.py
facetoolsz/core/stdex.py
facetoolsz/core/structex.py
facetoolsz/core/imagelib/SegIEPolys.py
facetoolsz/core/imagelib/__init__.py
facetoolsz/core/imagelib/blursharpen.py
facetoolsz/core/imagelib/color_transfer.py
facetoolsz/core/imagelib/common.py
facetoolsz/core/imagelib/draw.py
facetoolsz/core/imagelib/equalize_and_stack_square.py
facetoolsz/core/imagelib/ero_mask.py
facetoolsz/core/imagelib/estimate_sharpness.py
facetoolsz/core/imagelib/filters.py
facetoolsz/core/imagelib/morph.py
facetoolsz/core/imagelib/reduce_colors.py
facetoolsz/core/imagelib/warp.py
facetoolsz/core/imagelib/sd/__init__.py
facetoolsz/core/imagelib/sd/calc.py
facetoolsz/core/imagelib/sd/draw.py
facetoolsz/core/interact/__init__.py
facetoolsz/core/interact/interact.py
facetoolsz/core/joblib/MPClassFuncOnDemand.py
facetoolsz/core/joblib/MPFunc.py
facetoolsz/core/joblib/SubprocessGenerator.py
facetoolsz/core/joblib/SubprocessorBase.py
facetoolsz/core/joblib/ThisThreadGenerator.py
facetoolsz/core/joblib/__init__.py
facetoolsz/core/leras/__init__.py
facetoolsz/core/leras/device.py
facetoolsz/core/leras/nn.py
facetoolsz/core/leras/archis/0DeepFakeArchi.py
facetoolsz/core/leras/archis/ArchiBase.py
facetoolsz/core/leras/archis/DeepFakeArchi.py
facetoolsz/core/leras/archis/__init__.py
facetoolsz/core/leras/initializers/CA.py
facetoolsz/core/leras/initializers/__init__.py
facetoolsz/core/leras/layers/AdaIN.py
facetoolsz/core/leras/layers/BatchNorm2D.py
facetoolsz/core/leras/layers/BlurPool.py
facetoolsz/core/leras/layers/Conv2D.py
facetoolsz/core/leras/layers/Conv2DTranspose.py
facetoolsz/core/leras/layers/Dense.py
facetoolsz/core/leras/layers/DenseNorm.py
facetoolsz/core/leras/layers/DepthwiseConv2D.py
facetoolsz/core/leras/layers/FRNorm2D.py
facetoolsz-0.0.2.dist-info/LICENSE
facetoolsz-0.0.2.dist-info/METADATA
facetoolsz-0.0.2.dist-info/WHEEL
facetoolsz-0.0.2.dist-info/top_level.txt
facetoolsz-0.0.2.dist-info/RECORD
