Metadata-Version: 2.1
Name: facetoolsz
Version: 0.0.2
Summary: face image process lib
Home-page: UNKNOWN
Author: wvinzh
Author-email: wvinzh@qq.com
License: UNKNOWN
Platform: UNKNOWN
Classifier: Programming Language :: Python :: 3
Classifier: License :: OSI Approved :: GNU General Public License v3 (GPLv3)
Classifier: Operating System :: OS Independent
